aporia/__init__.py
aporia/main.py
aporia/aporia_ast/__init__.py
aporia/aporia_ast/main.py
aporia/interpreter/__init__.py
aporia/interpreter/main.py
aporia/interpreter/utils.py
aporia/parser/__init__.py
aporia/parser/grammar.lark
aporia/parser/parser.py
aporia/parser/transformer.py
aporia_interpreter-0.1.13.dist-info/METADATA
aporia_interpreter-0.1.13.dist-info/WHEEL
aporia_interpreter-0.1.13.dist-info/entry_points.txt
aporia_interpreter-0.1.13.dist-info/top_level.txt
aporia_interpreter-0.1.13.dist-info/RECORD
