Metadata-Version: 2.4
Name: aporia-interpreter
Version: 0.1.13
Summary: An interpreter for the Aporia language
Author-email: Ephraim Siegfried <ephraim.siegfried@hotmail.com>
Requires-Python: >=3.10
Requires-Dist: lark>=1.2.2
